{"tax_name": "species", "use_factor": true, "sample_factor": 1, "use_const_len": true, "const_len": 100000, "frags_num": 4, "cluster_names": ["s__Bacillus pumilus_M", "s__Bacillus amyloliquefaciens", "s__Bacillus zhangzhouensis", "s__Bacillus altitudinis", "s__Bacillus inaquosorum", "s__Bacillus pumilus_N", "s__Bacillus licheniformis_A", "s__Bacillus haynesii", "s__Bacillus paralicheniformis", "s__Bacillus nakamurai", "s__Bacillus atrophaeus", "s__Bacillus pumilus_G", "s__Bacillus gobiensis", "s__Bacillus vallismortis", "s__Bacillus licheniformis", "s__Bacillus australimaris", "s__Bacillus swezeyi", "s__Bacillus sonorensis_A", "s__Bacillus mojavensis", "s__Bacillus tequilensis", "s__Bacillus safensis", "s__Bacillus marinus", "s__Bacillus siamensis", "s__Bacillus pumilus", "s__Bacillus velezensis", "s__Bacillus glycinifermentans", "s__Bacillus sonorensis", "s__Bacillus subtilis", "s__Bacillus xiamenensis", "s__Bacillus halotolerans", "s__Bacillus subtilis_G"], "outdir": "g__Bacillus", "rep_time": 20}